PacoteCalculoMat/__init__.py
PacoteCalculoMat/calculos.py
PacoteCalculoMat-1.1.5.dist-info/METADATA
PacoteCalculoMat-1.1.5.dist-info/WHEEL
PacoteCalculoMat-1.1.5.dist-info/top_level.txt
PacoteCalculoMat-1.1.5.dist-info/RECORD
