Metadata-Version: 2.1
Name: PacoteCalculoMat
Version: 1.1.5
Summary: Meu primeiro pacote
Author: Milene Fialho
Author-email: milefialho16@gmail.com
License: MIT
